{
  "meta": {
    "version": "1.0.0",
    "lastUpdated": "2026-06-30T15:54:26.303Z",
    "currency": "USD"
  },
  "configurator": {
    "baseModels": {
      "isopoint---25ah-battery--2800-enclosure--300wh": {
        "name": "IsoPoint - 25Ah Battery ~ 2800 Enclosure ~ 300Wh",
        "capacity": "300Wh",
        "leadTime": "2-3 Weeks",
        "price": 265,
        "cogs": 185
      },
      "isopack---50ah-battery--3800-enclosure--600wh": {
        "name": "IsoPack - 50Ah Battery ~ 3800 Enclosure ~ 600Wh",
        "capacity": "600Wh",
        "leadTime": "2-3 weeks",
        "price": 329,
        "cogs": 230
      },
      "isostation---100ah-battery--4800-enclosure--12kwh": {
        "name": "IsoStation - 100Ah Battery ~ 4800 Enclosure ~ 1.2kWh",
        "capacity": "1.2kWh",
        "leadTime": "2-3 weeks",
        "price": 429,
        "cogs": 300
      }
    },
    "addons": {
      "inverter": {
        "_label": "AC Inverter",
        "none": {
          "label": "None (DC Only)",
          "price": 0,
          "cogs": 0,
          "models": []
        },
        "mqyjuov0": {
          "label": "300W Inverter",
          "price": 31,
          "cogs": 21,
          "models": [
            "isopoint---25ah-battery--2800-enclosure--300wh",
            "isopack---50ah-battery--3800-enclosure--600wh"
          ]
        },
        "mqyjuvq7": {
          "label": "500W Inverter",
          "price": 43,
          "cogs": 30,
          "models": [
            "isopoint---25ah-battery--2800-enclosure--300wh",
            "isopack---50ah-battery--3800-enclosure--600wh"
          ]
        },
        "mqyjv4he": {
          "label": "1000W Inverter",
          "price": 50,
          "cogs": 35,
          "models": [
            "isostation---100ah-battery--4800-enclosure--12kwh"
          ]
        },
        "mqyjvch3": {
          "label": "1600W Inverter",
          "price": 53,
          "cogs": 37,
          "models": [
            "iso-station"
          ]
        },
        "mqyjvk3m": {
          "label": "2200W Inverter",
          "price": 135,
          "cogs": 94,
          "models": [
            "iso-station"
          ]
        },
        "_subcategory": {
          "_label": "AC Outlet Count",
          "_hideWhenParent": "none",
          "mr0tp4me": {
            "label": "1 Outlet",
            "price": 0,
            "cogs": 0
          }
        }
      },
      "charger": {
        "_label": "Wall Charger",
        "standard": {
          "label": "Standard 10A",
          "price": 32,
          "cogs": 22
        },
        "fast": {
          "label": "Fast 20A",
          "price": 65,
          "cogs": 45,
          "models": []
        }
      },
      "12v": {
        "_label": "12V Outputs",
        "_subcategory": {
          "1": {
            "label": "1 Port",
            "price": 0,
            "cogs": 0
          },
          "2": {
            "label": "2 Ports",
            "price": 5,
            "cogs": 6,
            "models": []
          },
          "3": {
            "label": "3 Ports",
            "price": 9,
            "cogs": 9,
            "models": []
          },
          "_label": "12V Port Quantity",
          "_hideWhenParent": "none"
        },
        "none": {
          "label": "None",
          "price": 0,
          "cogs": 0
        },
        "anderson": {
          "label": "Anderson SB50",
          "price": 8,
          "cogs": 5,
          "models": [
            "iso-station",
            "isopack---50ah-lifepo4-06kwh"
          ]
        },
        "mqyj0i1u": {
          "label": "Cigarette Lighter Port",
          "price": 5,
          "cogs": 3
        }
      },
      "monitor": {
        "_label": "Battery Monitor",
        "led": {
          "label": "LED Indicator Only",
          "price": 3,
          "cogs": 2
        },
        "mqyj2zmv": {
          "label": "Voltage Monitor Only",
          "price": 5,
          "cogs": 3
        },
        "mqyj3syz": {
          "label": "Volt + Temp + Alarm Display",
          "price": 8,
          "cogs": 5
        },
        "mqyj4dam": {
          "label": "None",
          "price": 0,
          "cogs": 0
        }
      },
      "light": {
        "_label": "LED Work Light",
        "none": {
          "label": "None",
          "price": 0,
          "cogs": 0
        },
        "integrated": {
          "label": "Integrated (Built-in)",
          "price": 15,
          "cogs": 10
        },
        "mqyj4zvs": {
          "label": "External Flood Lights",
          "price": 10,
          "cogs": 5
        }
      },
      "usb": {
        "_label": "USB Ports",
        "none": {
          "label": "None",
          "price": 0,
          "cogs": 0
        },
        "mr0thmfi": {
          "label": "96W USB + USB-C ComboPort",
          "price": 0,
          "cogs": 0
        },
        "_subcategory": {
          "_label": "USB ComboPort Count",
          "_hideWhenParent": "none",
          "mr0tpwva": {
            "label": "1 Port",
            "price": 8,
            "cogs": 5
          },
          "mr0tqrpa": {
            "label": "2 Ports",
            "price": 14,
            "cogs": 10
          },
          "mr0tqyti": {
            "label": "3 Ports",
            "price": 20,
            "cogs": 15
          },
          "mr0tr2xa": {
            "label": "4 Ports",
            "price": 25,
            "cogs": 20
          }
        }
      }
    }
  }
}